heychat/__init__.py
heychat/_types.py
heychat/adapter.py
heychat/api.py
heychat/bot.py
heychat/channel.py
heychat/client.py
heychat/context.py
heychat/event.py
heychat/gateway.py
heychat/guild.py
heychat/mdmessage.py
heychat/message.py
heychat/receiver.py
heychat/requester.py
heychat/role.py
heychat/user.py
heychat/card/__init__.py
heychat/card/card.py
heychat/card/card_message.py
heychat/card/element.py
heychat/card/interface.py
heychat/card/module.py
heychat-0.0.15.dist-info/LICENSE
heychat-0.0.15.dist-info/METADATA
heychat-0.0.15.dist-info/WHEEL
heychat-0.0.15.dist-info/top_level.txt
heychat-0.0.15.dist-info/RECORD
