Metadata-Version: 2.1
Name: heychat
Version: 0.0.15
Summary: A Python SDK for heychat (黑盒语音)
Home-page: https://github.com/Edint386/heychat.py
Author: xsNight
Author-email: jason62570127@gmail.com
Classifier: Programming Language :: Python :: 3
Classifier: License :: OSI Approved :: MIT License
Classifier: Operating System :: OS Independent
Requires-Python: >=3.8
License-File: LICENSE
Requires-Dist: aiohttp
